pudu/__init__.py
pudu/assembly.py
pudu/calibration.py
pudu/plating.py
pudu/sample_preparation.py
pudu/transformation.py
pudu/utils.py
pudupy-1.0.0b7.dist-info/licenses/LICENSE
pudupy-1.0.0b7.dist-info/METADATA
pudupy-1.0.0b7.dist-info/WHEEL
pudupy-1.0.0b7.dist-info/top_level.txt
pudupy-1.0.0b7.dist-info/RECORD
