Metadata-Version: 2.4
Name: pudupy
Version: 1.0.0b7
Summary: Protocol Unified Design Unit
Author-email: Gonzalo Vidal <govi9038@colorado.edu>, Oscar Rodriguez <osro6012@colorado.edu>
Maintainer-email: Gonzalo Vidal <govi9038@colorado.edu>, Oscar Rodriguez <osro6012@colorado.edu>
License: MIT License
Project-URL: Homepage, https://github.com/MyersResearchGroup/PUDU
Project-URL: Bug Tracker, https://github.com/MyersResearchGroup/PUDU/issues
Keywords: pudu,lab,automation,opentrons,synthetic biology
Classifier: Programming Language :: Python :: 3
Classifier: License :: OSI Approved :: MIT License
Classifier: Operating System :: OS Independent
Requires-Python: >=3.7
License-File: LICENSE
Requires-Dist: opentrons>=8.4.1
Requires-Dist: xlsxwriter>=3.2.5
Provides-Extra: test
Requires-Dist: pytest>=7.0.0; extra == "test"
Requires-Dist: pytest-cov; extra == "test"
Dynamic: license-file
